{"name":"glalie","height":15,"gender_rate":4,"capture_rate":75,"base_experience":187,"moves":{"29":19,"43":1,"44":10,"58":0,"59":0,"63":0,"89":0,"92":0,"104":0,"113":0,"148":0,"153":0,"156":0,"164":0,"181":1,"182":0,"196":13,"207":0,"213":0,"216":0,"218":0,"219":0,"237":0,"240":0,"242":31,"247":0,"258":0,"259":0,"263":0,"269":0,"329":59,"360":0,"371":0,"416":0,"423":28,"496":0,"523":0,"524":0},"types":[15],"stats":{"hp":80,"attack":80,"defense":80,"sAttack":80,"sDefense":80,"speed":80},"growth_rate":2}