{"name":"wartortle","height":10,"gender_rate":1,"capture_rate":45,"base_experience":143,"moves":{"33":1,"39":4,"44":16,"55":13,"56":48,"57":0,"58":0,"59":0,"70":0,"91":0,"92":0,"104":0,"110":10,"127":0,"130":36,"145":7,"156":0,"164":0,"182":0,"207":0,"213":0,"216":0,"218":0,"229":20,"237":0,"240":0,"249":0,"258":0,"263":0,"280":0,"291":0,"317":0,"334":40,"352":28,"360":0,"374":0,"401":32,"496":0,"503":0,"518":0},"types":[11],"stats":{"hp":59,"attack":63,"defense":80,"sAttack":65,"sDefense":80,"speed":58},"growth_rate":4,"evolves_to":{"id":9,"level":36}}