{"name":"quilava","height":9,"gender_rate":1,"capture_rate":45,"base_experience":142,"moves":{"15":0,"33":1,"38":64,"43":1,"46":0,"52":10,"53":0,"70":0,"91":0,"92":0,"98":13,"104":0,"108":6,"111":24,"126":0,"129":31,"156":0,"164":0,"172":20,"182":0,"205":57,"207":0,"213":0,"216":0,"218":0,"237":0,"241":0,"249":0,"261":0,"263":0,"280":0,"284":68,"315":0,"332":0,"436":42,"488":0,"496":0,"510":0,"517":53,"519":0,"528":0},"types":[10],"stats":{"hp":58,"attack":64,"defense":58,"sAttack":80,"sDefense":65,"speed":80},"growth_rate":4,"evolves_to":{"id":157,"level":36}}